roh_moo_hyun/__init__.py
roh_moo_hyun/cli.py
roh_moo_hyun/extract_speech_from_pdf.py
roh_moo_hyun/db/__init__.py
roh_moo_hyun/db/connection_manager.py
roh_moo_hyun/db/init.db
roh_moo_hyun/db/search.py
roh_moo_hyun-0.4.1.dist-info/METADATA
roh_moo_hyun-0.4.1.dist-info/WHEEL
roh_moo_hyun-0.4.1.dist-info/entry_points.txt
roh_moo_hyun-0.4.1.dist-info/top_level.txt
roh_moo_hyun-0.4.1.dist-info/RECORD
