Metadata-Version: 2.1
Name: roh-moo-hyun
Version: 0.4.1
Author-email: becky2sawyer <becky2sawyer@gmail.com>
License: MIT
Project-URL: Homepage, https://github.com/becky2sawyer/roh-moo-hyun
Project-URL: Bug Tracker, https://github.com/becky2sawyer/roh-moo-hyun/issues
Requires-Python: >=3.9
Requires-Dist: requests >=2.31.0
Requires-Dist: pypdf >=3.15.5
Requires-Dist: pandas >=2.1.0
Requires-Dist: pyarrow >=13.0.0
Requires-Dist: fastparquet >=2023.8.0
